<?xml version="1.0" encoding="UTF-8"?>
<objects serializationModel="Studio.02.02.00">
	<object class="ParameterPreset" id="{e4b0beae-af97-4910-a7c8-1bae3cf63065}">
		<property name="name">
			<value>MusicPlaying</value>
		</property>
		<relationship name="folder">
			<destination>{a7d2d14d-8d00-4647-8179-9d23b2431cf8}</destination>
		</relationship>
		<relationship name="parameter">
			<destination>{9e67bd3c-8ccc-4921-bf64-bc3c212abcc5}</destination>
		</relationship>
	</object>
	<object class="GameParameter" id="{9e67bd3c-8ccc-4921-bf64-bc3c212abcc5}">
		<property name="parameterType">
			<value>2</value>
		</property>
		<property name="maximum">
			<value>2</value>
		</property>
		<property name="enumerationLabels">
			<value>False</value>
			<value>True</value>
		</property>
		<property name="initialValue">
			<value>0</value>
		</property>
	</object>
</objects>
